jpl/__init__.py
jpl/__main__.py
jpl/lint.py
jpl/cli/__init__.py
jpl/cli/config.py
jpl/cli/main_cli.py
jpl/rules/__init__.py
jpl/rules/jiggyrule.py
jpl/rules/pipeline/__init__.py
jpl/rules/pipeline/pipeline.py
jpl/rules/playbook/__init__.py
jpl/rules/playbook/info.py
jpl/rules/task/__init__.py
jpl/rules/task/function.py
jpl/rules/task/task.py
jpl/utils/__init__.py
jpl/utils/path.py
jpl-0.0.3.dist-info/LICENSE
jpl-0.0.3.dist-info/METADATA
jpl-0.0.3.dist-info/WHEEL
jpl-0.0.3.dist-info/entry_points.txt
jpl-0.0.3.dist-info/top_level.txt
jpl-0.0.3.dist-info/RECORD
