Metadata-Version: 2.1
Name: jpl
Version: 0.0.3
Summary: Jiggy Playbook Linter
Home-page: https://github.com/thejig/jpl
Author: Mitchell Bregman, Leon Kozlowski
Author-email: mitchbregs@gmail.com, leonkozlowski@gmail.com
License: UNKNOWN
Keywords: yaml lint linter
Platform: UNKNOWN
Classifier: Programming Language :: Python :: 3
Classifier: License :: OSI Approved :: MIT License
Classifier: Operating System :: OS Independent
Requires-Python: >=3.7
Requires-Dist: pytest
Requires-Dist: pyyaml
Requires-Dist: Click
